httpie_credential_store/__init__.py
httpie_credential_store/_auth.py
httpie_credential_store/_keychain.py
httpie_credential_store/_plugin.py
httpie_credential_store/_store.py
httpie_credential_store-3.1.0.dist-info/METADATA
httpie_credential_store-3.1.0.dist-info/WHEEL
httpie_credential_store-3.1.0.dist-info/entry_points.txt
httpie_credential_store-3.1.0.dist-info/RECORD
